ghostbusterV4/__init__.py
ghostbusterV4/cli.py
ghostbusterV4/scan.py
ghostbusterV4/version.py
ghostbusterV4-1.0.8.dist-info/LICENSE
ghostbusterV4-1.0.8.dist-info/METADATA
ghostbusterV4-1.0.8.dist-info/WHEEL
ghostbusterV4-1.0.8.dist-info/entry_points.txt
ghostbusterV4-1.0.8.dist-info/top_level.txt
ghostbusterV4-1.0.8.dist-info/RECORD
